alphabacktest/__init__.py
alphabacktest/_dash_results.py
alphabacktest/alphabacktest.py
alphabacktest/cli.py
alphabacktest/assets/header.css
alphabacktest/assets/typography.css
alphabacktest-1.0.0.dist-info/AUTHORS.rst
alphabacktest-1.0.0.dist-info/LICENSE
alphabacktest-1.0.0.dist-info/METADATA
alphabacktest-1.0.0.dist-info/WHEEL
alphabacktest-1.0.0.dist-info/entry_points.txt
alphabacktest-1.0.0.dist-info/top_level.txt
alphabacktest-1.0.0.dist-info/RECORD
