Metadata-Version: 2.1
Name: alphabacktest
Version: 1.0.0
Summary: Module for backtesting algorithmic trading strategies
Home-page: https://github.com/serginc21/alphabacktest
Author: Sergi Novellas
Author-email: sernocr@gmail.com
License: MIT license
Keywords: alphabacktest
Platform: UNKNOWN
Classifier: Development Status :: 2 - Pre-Alpha
Classifier: Intended Audience :: Developers
Classifier: License :: OSI Approved :: MIT License
Classifier: Natural Language :: English
Classifier: Programming Language :: Python :: 3
Classifier: Programming Language :: Python :: 3.6
Classifier: Programming Language :: Python :: 3.7
Classifier: Programming Language :: Python :: 3.8
Requires-Python: >=3.6
Requires-Dist: Click (>=7.0)
Requires-Dist: progressbar2 (>=3.53.1)
Requires-Dist: pandas (>=1.1.4)
Requires-Dist: pandas-datareader (>=0.9.0)
